SocketUI/__init__.py
SocketUI/ui.py
SocketUI-0.0.2.dist-info/METADATA
SocketUI-0.0.2.dist-info/WHEEL
SocketUI-0.0.2.dist-info/entry_points.txt
SocketUI-0.0.2.dist-info/top_level.txt
SocketUI-0.0.2.dist-info/RECORD
